argparse_dataclass.py
argparse_dataclass-2.0.0.dist-info/LICENSE
argparse_dataclass-2.0.0.dist-info/METADATA
argparse_dataclass-2.0.0.dist-info/WHEEL
argparse_dataclass-2.0.0.dist-info/top_level.txt
argparse_dataclass-2.0.0.dist-info/RECORD
