Metadata-Version: 2.1
Name: argparse_dataclass
Version: 2.0.0
Summary: Declarative CLIs with argparse and dataclasses
Home-page: https://github.com/mivade/argparse_dataclass
Author: Michael V. DePalatis
Author-email: mike@depalatis.net
Classifier: License :: OSI Approved :: MIT License
Classifier: Operating System :: OS Independent
Classifier: Programming Language :: Python :: 3
Classifier: Programming Language :: Python :: 3.8
Classifier: Programming Language :: Python :: 3.9
Classifier: Programming Language :: Python :: 3.10
Classifier: Programming Language :: Python :: 3.11
Requires-Python: >=3.8
License-File: LICENSE
